{
  "C:\\Users\\chopd\\OneDrive\\Desktop\\MERN-Stack\\_____working project\\chaturai-pratiyogita\\server\\serverless.yml": {
    "versionFramework": "4.6.2",
    "servicePath": "C:\\Users\\chopd\\OneDrive\\Desktop\\MERN-Stack\\_____working project\\chaturai-pratiyogita\\server\\serverless.yml",
    "serviceConfigFileName": "serverless.yml",
    "service": {
      "org": "harshitchopde",
      "app": "quiz-web-server",
      "service": "quiz-server-api",
      "provider": {
        "name": "aws",
        "runtime": "nodejs20.x",
        "timeout": 20,
        "region": "ap-south-1",
        "httpApi": {
          "cors": {
            "allowedOrigins": [
              "*"
            ],
            "allowedMethods": [
              "GET",
              "POST",
              "PUT",
              "DELETE",
              "OPTIONS"
            ],
            "allowedHeaders": [
              "Content-Type",
              "Authorization"
            ],
            "allowCredentials": "<REDACTED>"
          }
        },
        "stage": "dev",
        "versionFunctions": true,
        "compiledCloudFormationTemplate": {
          "AWSTemplateFormatVersion": "2010-09-09",
          "Description": "The AWS CloudFormation template for this Serverless application",
          "Resources": {
            "ApiLogGroup": {
              "Type": "AWS::Logs::LogGroup",
              "Properties": {
                "LogGroupName": "/aws/lambda/quiz-server-api-dev-api"
              }
            },
            "IamRoleLambdaExecution": {
              "Type": "AWS::IAM::Role",
              "Properties": {
                "AssumeRolePolicyDocument": {
                  "Version": "2012-10-17",
                  "Statement": [
                    {
                      "Effect": "Allow",
                      "Principal": {
                        "Service": [
                          "lambda.amazonaws.com"
                        ]
                      },
                      "Action": [
                        "sts:AssumeRole"
                      ]
                    }
                  ]
                },
                "Policies": [
                  {
                    "PolicyName": {
                      "Fn::Join": [
                        "-",
                        [
                          "quiz-server-api",
                          "dev",
                          "lambda"
                        ]
                      ]
                    },
                    "PolicyDocument": {
                      "Version": "2012-10-17",
                      "Statement": [
                        {
                          "Effect": "Allow",
                          "Action": [
                            "logs:CreateLogStream",
                            "logs:CreateLogGroup",
                            "logs:TagResource"
                          ],
                          "Resource": [
                            {
                              "Fn::Sub": "arn:${AWS::Partition}:logs:${AWS::Region}:${AWS::AccountId}:log-group:/aws/lambda/quiz-server-api-dev*:*"
                            }
                          ]
                        },
                        {
                          "Effect": "Allow",
                          "Action": [
                            "logs:PutLogEvents"
                          ],
                          "Resource": [
                            {
                              "Fn::Sub": "arn:${AWS::Partition}:logs:${AWS::Region}:${AWS::AccountId}:log-group:/aws/lambda/quiz-server-api-dev*:*:*"
                            }
                          ]
                        }
                      ]
                    }
                  }
                ],
                "Path": "/",
                "RoleName": {
                  "Fn::Join": [
                    "-",
                    [
                      "quiz-server-api",
                      "dev",
                      {
                        "Ref": "AWS::Region"
                      },
                      "lambdaRole"
                    ]
                  ]
                }
              }
            },
            "ApiLambdaFunction": {
              "Type": "AWS::Lambda::Function",
              "Properties": {
                "Code": {
                  "S3Bucket": "serverless-framework-deployments-ap-south-1-742a1e34-61d6",
                  "S3Key": "serverless/quiz-server-api/dev/1739110905896-2025-02-09T14:21:45.896Z/quiz-server-api.zip"
                },
                "Handler": "index.handler",
                "Runtime": "nodejs20.x",
                "FunctionName": "quiz-server-api-dev-api",
                "MemorySize": 1024,
                "Timeout": 20,
                "Role": {
                  "Fn::GetAtt": [
                    "IamRoleLambdaExecution",
                    "Arn"
                  ]
                }
              },
              "DependsOn": [
                "ApiLogGroup"
              ]
            },
            "ApiLambdaVersionucJb9unkVGZN83FPovi10Pyw8aHIKK984d0FMMuw": {
              "Type": "AWS::Lambda::Version",
              "DeletionPolicy": "Retain",
              "Properties": {
                "FunctionName": {
                  "Ref": "ApiLambdaFunction"
                },
                "CodeSha256": "vnN0Lm6u5nO4Z65pNUbM9hUlzMwt/ixXOHCSuOYICvE="
              }
            },
            "HttpApi": {
              "Type": "AWS::ApiGatewayV2::Api",
              "Properties": {
                "Name": "dev-quiz-server-api",
                "ProtocolType": "HTTP",
                "CorsConfiguration": {
                  "AllowCredentials": "<REDACTED>",
                  "AllowHeaders": [
                    "Content-Type",
                    "Authorization"
                  ],
                  "AllowMethods": [
                    "GET",
                    "POST",
                    "PUT",
                    "DELETE",
                    "OPTIONS"
                  ],
                  "AllowOrigins": [
                    "*"
                  ]
                }
              }
            },
            "HttpApiStage": {
              "Type": "AWS::ApiGatewayV2::Stage",
              "Properties": {
                "ApiId": {
                  "Ref": "HttpApi"
                },
                "StageName": "$default",
                "AutoDeploy": true,
                "DefaultRouteSettings": {
                  "DetailedMetricsEnabled": false
                }
              }
            },
            "ApiLambdaPermissionHttpApi": {
              "Type": "AWS::Lambda::Permission",
              "Properties": {
                "FunctionName": {
                  "Fn::GetAtt": [
                    "ApiLambdaFunction",
                    "Arn"
                  ]
                },
                "Action": "lambda:InvokeFunction",
                "Principal": "apigateway.amazonaws.com",
                "SourceArn": {
                  "Fn::Join": [
                    "",
                    [
                      "arn:",
                      {
                        "Ref": "AWS::Partition"
                      },
                      ":execute-api:",
                      {
                        "Ref": "AWS::Region"
                      },
                      ":",
                      {
                        "Ref": "AWS::AccountId"
                      },
                      ":",
                      {
                        "Ref": "HttpApi"
                      },
                      "/*"
                    ]
                  ]
                }
              }
            },
            "HttpApiIntegrationApi": {
              "Type": "AWS::ApiGatewayV2::Integration",
              "Properties": {
                "ApiId": {
                  "Ref": "HttpApi"
                },
                "IntegrationType": "AWS_PROXY",
                "IntegrationUri": {
                  "Fn::GetAtt": [
                    "ApiLambdaFunction",
                    "Arn"
                  ]
                },
                "PayloadFormatVersion": "2.0",
                "TimeoutInMillis": 30000
              }
            },
            "HttpApiRouteAnyProxyVar": {
              "Type": "AWS::ApiGatewayV2::Route",
              "Properties": {
                "ApiId": {
                  "Ref": "HttpApi"
                },
                "RouteKey": "ANY /{proxy+}",
                "Target": {
                  "Fn::Join": [
                    "/",
                    [
                      "integrations",
                      {
                        "Ref": "HttpApiIntegrationApi"
                      }
                    ]
                  ]
                }
              },
              "DependsOn": "HttpApiIntegrationApi"
            }
          },
          "Outputs": {
            "ServerlessDeploymentBucketName": {
              "Value": "serverless-framework-deployments-ap-south-1-742a1e34-61d6",
              "Export": {
                "Name": "sls-quiz-server-api-dev-ServerlessDeploymentBucketName"
              }
            },
            "ApiLambdaFunctionQualifiedArn": {
              "Description": "Current Lambda function version",
              "Value": {
                "Ref": "ApiLambdaVersionucJb9unkVGZN83FPovi10Pyw8aHIKK984d0FMMuw"
              },
              "Export": {
                "Name": "sls-quiz-server-api-dev-ApiLambdaFunctionQualifiedArn"
              }
            },
            "HttpApiId": {
              "Description": "Id of the HTTP API",
              "Value": {
                "Ref": "HttpApi"
              },
              "Export": {
                "Name": "sls-quiz-server-api-dev-HttpApiId"
              }
            },
            "HttpApiUrl": {
              "Description": "URL of the HTTP API",
              "Value": {
                "Fn::Join": [
                  "",
                  [
                    "https://",
                    {
                      "Ref": "HttpApi"
                    },
                    ".execute-api.",
                    {
                      "Ref": "AWS::Region"
                    },
                    ".",
                    {
                      "Ref": "AWS::URLSuffix"
                    }
                  ]
                ]
              },
              "Export": {
                "Name": "sls-quiz-server-api-dev-HttpApiUrl"
              }
            }
          }
        },
        "vpc": {}
      },
      "functions": {
        "api": {
          "handler": "index.handler",
          "events": [
            {
              "httpApi": {
                "path": "/{proxy+}",
                "method": "any"
              },
              "resolvedMethod": "ANY",
              "resolvedPath": "/{proxy+}"
            }
          ],
          "name": "quiz-server-api-dev-api",
          "package": {},
          "memory": 1024,
          "timeout": 20,
          "runtime": "nodejs20.x",
          "vpc": {},
          "versionLogicalId": "ApiLambdaVersionucJb9unkVGZN83FPovi10Pyw8aHIKK984d0FMMuw"
        }
      },
      "plugins": [
        "serverless-offline"
      ]
    },
    "provider": {
      "name": "aws",
      "runtime": "nodejs20.x",
      "timeout": 20,
      "region": "ap-south-1",
      "httpApi": {
        "cors": {
          "allowedOrigins": [
            "*"
          ],
          "allowedMethods": [
            "GET",
            "POST",
            "PUT",
            "DELETE",
            "OPTIONS"
          ],
          "allowedHeaders": [
            "Content-Type",
            "Authorization"
          ],
          "allowCredentials": "<REDACTED>"
        }
      },
      "stage": "dev",
      "versionFunctions": true,
      "compiledCloudFormationTemplate": {
        "AWSTemplateFormatVersion": "2010-09-09",
        "Description": "The AWS CloudFormation template for this Serverless application",
        "Resources": {
          "ApiLogGroup": {
            "Type": "AWS::Logs::LogGroup",
            "Properties": {
              "LogGroupName": "/aws/lambda/quiz-server-api-dev-api"
            }
          },
          "IamRoleLambdaExecution": {
            "Type": "AWS::IAM::Role",
            "Properties": {
              "AssumeRolePolicyDocument": {
                "Version": "2012-10-17",
                "Statement": [
                  {
                    "Effect": "Allow",
                    "Principal": {
                      "Service": [
                        "lambda.amazonaws.com"
                      ]
                    },
                    "Action": [
                      "sts:AssumeRole"
                    ]
                  }
                ]
              },
              "Policies": [
                {
                  "PolicyName": {
                    "Fn::Join": [
                      "-",
                      [
                        "quiz-server-api",
                        "dev",
                        "lambda"
                      ]
                    ]
                  },
                  "PolicyDocument": {
                    "Version": "2012-10-17",
                    "Statement": [
                      {
                        "Effect": "Allow",
                        "Action": [
                          "logs:CreateLogStream",
                          "logs:CreateLogGroup",
                          "logs:TagResource"
                        ],
                        "Resource": [
                          {
                            "Fn::Sub": "arn:${AWS::Partition}:logs:${AWS::Region}:${AWS::AccountId}:log-group:/aws/lambda/quiz-server-api-dev*:*"
                          }
                        ]
                      },
                      {
                        "Effect": "Allow",
                        "Action": [
                          "logs:PutLogEvents"
                        ],
                        "Resource": [
                          {
                            "Fn::Sub": "arn:${AWS::Partition}:logs:${AWS::Region}:${AWS::AccountId}:log-group:/aws/lambda/quiz-server-api-dev*:*:*"
                          }
                        ]
                      }
                    ]
                  }
                }
              ],
              "Path": "/",
              "RoleName": {
                "Fn::Join": [
                  "-",
                  [
                    "quiz-server-api",
                    "dev",
                    {
                      "Ref": "AWS::Region"
                    },
                    "lambdaRole"
                  ]
                ]
              }
            }
          },
          "ApiLambdaFunction": {
            "Type": "AWS::Lambda::Function",
            "Properties": {
              "Code": {
                "S3Bucket": "serverless-framework-deployments-ap-south-1-742a1e34-61d6",
                "S3Key": "serverless/quiz-server-api/dev/1739110905896-2025-02-09T14:21:45.896Z/quiz-server-api.zip"
              },
              "Handler": "index.handler",
              "Runtime": "nodejs20.x",
              "FunctionName": "quiz-server-api-dev-api",
              "MemorySize": 1024,
              "Timeout": 20,
              "Role": {
                "Fn::GetAtt": [
                  "IamRoleLambdaExecution",
                  "Arn"
                ]
              }
            },
            "DependsOn": [
              "ApiLogGroup"
            ]
          },
          "ApiLambdaVersionucJb9unkVGZN83FPovi10Pyw8aHIKK984d0FMMuw": {
            "Type": "AWS::Lambda::Version",
            "DeletionPolicy": "Retain",
            "Properties": {
              "FunctionName": {
                "Ref": "ApiLambdaFunction"
              },
              "CodeSha256": "vnN0Lm6u5nO4Z65pNUbM9hUlzMwt/ixXOHCSuOYICvE="
            }
          },
          "HttpApi": {
            "Type": "AWS::ApiGatewayV2::Api",
            "Properties": {
              "Name": "dev-quiz-server-api",
              "ProtocolType": "HTTP",
              "CorsConfiguration": {
                "AllowCredentials": "<REDACTED>",
                "AllowHeaders": [
                  "Content-Type",
                  "Authorization"
                ],
                "AllowMethods": [
                  "GET",
                  "POST",
                  "PUT",
                  "DELETE",
                  "OPTIONS"
                ],
                "AllowOrigins": [
                  "*"
                ]
              }
            }
          },
          "HttpApiStage": {
            "Type": "AWS::ApiGatewayV2::Stage",
            "Properties": {
              "ApiId": {
                "Ref": "HttpApi"
              },
              "StageName": "$default",
              "AutoDeploy": true,
              "DefaultRouteSettings": {
                "DetailedMetricsEnabled": false
              }
            }
          },
          "ApiLambdaPermissionHttpApi": {
            "Type": "AWS::Lambda::Permission",
            "Properties": {
              "FunctionName": {
                "Fn::GetAtt": [
                  "ApiLambdaFunction",
                  "Arn"
                ]
              },
              "Action": "lambda:InvokeFunction",
              "Principal": "apigateway.amazonaws.com",
              "SourceArn": {
                "Fn::Join": [
                  "",
                  [
                    "arn:",
                    {
                      "Ref": "AWS::Partition"
                    },
                    ":execute-api:",
                    {
                      "Ref": "AWS::Region"
                    },
                    ":",
                    {
                      "Ref": "AWS::AccountId"
                    },
                    ":",
                    {
                      "Ref": "HttpApi"
                    },
                    "/*"
                  ]
                ]
              }
            }
          },
          "HttpApiIntegrationApi": {
            "Type": "AWS::ApiGatewayV2::Integration",
            "Properties": {
              "ApiId": {
                "Ref": "HttpApi"
              },
              "IntegrationType": "AWS_PROXY",
              "IntegrationUri": {
                "Fn::GetAtt": [
                  "ApiLambdaFunction",
                  "Arn"
                ]
              },
              "PayloadFormatVersion": "2.0",
              "TimeoutInMillis": 30000
            }
          },
          "HttpApiRouteAnyProxyVar": {
            "Type": "AWS::ApiGatewayV2::Route",
            "Properties": {
              "ApiId": {
                "Ref": "HttpApi"
              },
              "RouteKey": "ANY /{proxy+}",
              "Target": {
                "Fn::Join": [
                  "/",
                  [
                    "integrations",
                    {
                      "Ref": "HttpApiIntegrationApi"
                    }
                  ]
                ]
              }
            },
            "DependsOn": "HttpApiIntegrationApi"
          }
        },
        "Outputs": {
          "ServerlessDeploymentBucketName": {
            "Value": "serverless-framework-deployments-ap-south-1-742a1e34-61d6",
            "Export": {
              "Name": "sls-quiz-server-api-dev-ServerlessDeploymentBucketName"
            }
          },
          "ApiLambdaFunctionQualifiedArn": {
            "Description": "Current Lambda function version",
            "Value": {
              "Ref": "ApiLambdaVersionucJb9unkVGZN83FPovi10Pyw8aHIKK984d0FMMuw"
            },
            "Export": {
              "Name": "sls-quiz-server-api-dev-ApiLambdaFunctionQualifiedArn"
            }
          },
          "HttpApiId": {
            "Description": "Id of the HTTP API",
            "Value": {
              "Ref": "HttpApi"
            },
            "Export": {
              "Name": "sls-quiz-server-api-dev-HttpApiId"
            }
          },
          "HttpApiUrl": {
            "Description": "URL of the HTTP API",
            "Value": {
              "Fn::Join": [
                "",
                [
                  "https://",
                  {
                    "Ref": "HttpApi"
                  },
                  ".execute-api.",
                  {
                    "Ref": "AWS::Region"
                  },
                  ".",
                  {
                    "Ref": "AWS::URLSuffix"
                  }
                ]
              ]
            },
            "Export": {
              "Name": "sls-quiz-server-api-dev-HttpApiUrl"
            }
          }
        }
      },
      "vpc": {}
    },
    "dashboard": {
      "isEnabledForService": true,
      "requiredAuthentication": false,
      "orgFeaturesInUse": {
        "providers": false,
        "monitoring": false
      },
      "orgObservabilityIntegrations": null,
      "serviceAppId": "SWY3dXRYtDQfTcXQxh",
      "serviceProvider": null,
      "instanceParameters": null
    },
    "serviceRawFile": "org: harshitchopde\napp: quiz-web-server\nservice: quiz-server-api\n\nprovider:\n  name: aws\n  runtime: nodejs20.x\n  timeout: 20\n  region: ap-south-1\n  httpApi:\n    cors: \n      allowedOrigins:\n        - \"*\"  # Change to \"http://localhost:3000\" for security\n      allowedMethods:\n        - GET\n        - POST\n        - PUT\n        - DELETE\n        - OPTIONS\n      allowedHeaders:\n        - Content-Type\n        - Authorization\n      allowCredentials: false\n\nfunctions:\n  api:\n    handler: index.handler\n    events:\n      - httpApi:\n          path: /{proxy+}  # Wildcard routing for all paths\n          method: any\n\nplugins:\n  - serverless-offline\n",
    "command": [
      "deploy"
    ],
    "options": {},
    "orgId": "a9dce40d-d992-4bfb-b075-45e0eff25506",
    "orgName": "harshitchopde",
    "userId": "WHrxh9Yxj6mS1rbHSq",
    "userName": "harshitchopde",
    "serviceProviderAwsAccountId": "457272581074",
    "serviceProviderAwsCfStackName": "quiz-server-api-dev",
    "serviceProviderAwsCfStackId": "arn:aws:cloudformation:ap-south-1:457272581074:stack/quiz-server-api-dev/48cc9430-e6e9-11ef-a1ab-06dddfe15eaf",
    "serviceProviderAwsCfStackCreated": "2025-02-09T13:25:09.571Z",
    "serviceProviderAwsCfStackUpdated": "2025-02-09T13:49:32.471Z",
    "serviceProviderAwsCfStackStatus": "UPDATE_COMPLETE",
    "serviceProviderAwsCfStackOutputs": [
      {
        "OutputKey": "ApiLambdaFunctionQualifiedArn",
        "OutputValue": "arn:aws:lambda:ap-south-1:457272581074:function:quiz-server-api-dev-api:9",
        "Description": "Current Lambda function version",
        "ExportName": "sls-quiz-server-api-dev-ApiLambdaFunctionQualifiedArn"
      },
      {
        "OutputKey": "HttpApiId",
        "OutputValue": "pgqd6k5i2i",
        "Description": "Id of the HTTP API",
        "ExportName": "sls-quiz-server-api-dev-HttpApiId"
      },
      {
        "OutputKey": "ServerlessDeploymentBucketName",
        "OutputValue": "serverless-framework-deployments-ap-south-1-742a1e34-61d6",
        "ExportName": "sls-quiz-server-api-dev-ServerlessDeploymentBucketName"
      },
      {
        "OutputKey": "HttpApiUrl",
        "OutputValue": "https://pgqd6k5i2i.execute-api.ap-south-1.amazonaws.com",
        "Description": "URL of the HTTP API",
        "ExportName": "sls-quiz-server-api-dev-HttpApiUrl"
      }
    ],
    "compiledCloudFormationTemplate": {
      "AWSTemplateFormatVersion": "2010-09-09",
      "Description": "The AWS CloudFormation template for this Serverless application",
      "Resources": {
        "ApiLogGroup": {
          "Type": "AWS::Logs::LogGroup",
          "Properties": {
            "LogGroupName": "/aws/lambda/quiz-server-api-dev-api"
          }
        },
        "IamRoleLambdaExecution": {
          "Type": "AWS::IAM::Role",
          "Properties": {
            "AssumeRolePolicyDocument": {
              "Version": "2012-10-17",
              "Statement": [
                {
                  "Effect": "Allow",
                  "Principal": {
                    "Service": [
                      "lambda.amazonaws.com"
                    ]
                  },
                  "Action": [
                    "sts:AssumeRole"
                  ]
                }
              ]
            },
            "Policies": [
              {
                "PolicyName": {
                  "Fn::Join": [
                    "-",
                    [
                      "quiz-server-api",
                      "dev",
                      "lambda"
                    ]
                  ]
                },
                "PolicyDocument": {
                  "Version": "2012-10-17",
                  "Statement": [
                    {
                      "Effect": "Allow",
                      "Action": [
                        "logs:CreateLogStream",
                        "logs:CreateLogGroup",
                        "logs:TagResource"
                      ],
                      "Resource": [
                        {
                          "Fn::Sub": "arn:${AWS::Partition}:logs:${AWS::Region}:${AWS::AccountId}:log-group:/aws/lambda/quiz-server-api-dev*:*"
                        }
                      ]
                    },
                    {
                      "Effect": "Allow",
                      "Action": [
                        "logs:PutLogEvents"
                      ],
                      "Resource": [
                        {
                          "Fn::Sub": "arn:${AWS::Partition}:logs:${AWS::Region}:${AWS::AccountId}:log-group:/aws/lambda/quiz-server-api-dev*:*:*"
                        }
                      ]
                    }
                  ]
                }
              }
            ],
            "Path": "/",
            "RoleName": {
              "Fn::Join": [
                "-",
                [
                  "quiz-server-api",
                  "dev",
                  {
                    "Ref": "AWS::Region"
                  },
                  "lambdaRole"
                ]
              ]
            }
          }
        },
        "ApiLambdaFunction": {
          "Type": "AWS::Lambda::Function",
          "Properties": {
            "Code": {
              "S3Bucket": "serverless-framework-deployments-ap-south-1-742a1e34-61d6",
              "S3Key": "serverless/quiz-server-api/dev/1739110905896-2025-02-09T14:21:45.896Z/quiz-server-api.zip"
            },
            "Handler": "index.handler",
            "Runtime": "nodejs20.x",
            "FunctionName": "quiz-server-api-dev-api",
            "MemorySize": 1024,
            "Timeout": 20,
            "Role": {
              "Fn::GetAtt": [
                "IamRoleLambdaExecution",
                "Arn"
              ]
            }
          },
          "DependsOn": [
            "ApiLogGroup"
          ]
        },
        "ApiLambdaVersionucJb9unkVGZN83FPovi10Pyw8aHIKK984d0FMMuw": {
          "Type": "AWS::Lambda::Version",
          "DeletionPolicy": "Retain",
          "Properties": {
            "FunctionName": {
              "Ref": "ApiLambdaFunction"
            },
            "CodeSha256": "vnN0Lm6u5nO4Z65pNUbM9hUlzMwt/ixXOHCSuOYICvE="
          }
        },
        "HttpApi": {
          "Type": "AWS::ApiGatewayV2::Api",
          "Properties": {
            "Name": "dev-quiz-server-api",
            "ProtocolType": "HTTP",
            "CorsConfiguration": {
              "AllowHeaders": [
                "Content-Type",
                "Authorization"
              ],
              "AllowMethods": [
                "GET",
                "POST",
                "PUT",
                "DELETE",
                "OPTIONS"
              ],
              "AllowOrigins": [
                "*"
              ]
            }
          }
        },
        "HttpApiStage": {
          "Type": "AWS::ApiGatewayV2::Stage",
          "Properties": {
            "ApiId": {
              "Ref": "HttpApi"
            },
            "StageName": "$default",
            "AutoDeploy": true,
            "DefaultRouteSettings": {
              "DetailedMetricsEnabled": false
            }
          }
        },
        "ApiLambdaPermissionHttpApi": {
          "Type": "AWS::Lambda::Permission",
          "Properties": {
            "FunctionName": {
              "Fn::GetAtt": [
                "ApiLambdaFunction",
                "Arn"
              ]
            },
            "Action": "lambda:InvokeFunction",
            "Principal": "apigateway.amazonaws.com",
            "SourceArn": {
              "Fn::Join": [
                "",
                [
                  "arn:",
                  {
                    "Ref": "AWS::Partition"
                  },
                  ":execute-api:",
                  {
                    "Ref": "AWS::Region"
                  },
                  ":",
                  {
                    "Ref": "AWS::AccountId"
                  },
                  ":",
                  {
                    "Ref": "HttpApi"
                  },
                  "/*"
                ]
              ]
            }
          }
        },
        "HttpApiIntegrationApi": {
          "Type": "AWS::ApiGatewayV2::Integration",
          "Properties": {
            "ApiId": {
              "Ref": "HttpApi"
            },
            "IntegrationType": "AWS_PROXY",
            "IntegrationUri": {
              "Fn::GetAtt": [
                "ApiLambdaFunction",
                "Arn"
              ]
            },
            "PayloadFormatVersion": "2.0",
            "TimeoutInMillis": 30000
          }
        },
        "HttpApiRouteAnyProxyVar": {
          "Type": "AWS::ApiGatewayV2::Route",
          "Properties": {
            "ApiId": {
              "Ref": "HttpApi"
            },
            "RouteKey": "ANY /{proxy+}",
            "Target": {
              "Fn::Join": [
                "/",
                [
                  "integrations",
                  {
                    "Ref": "HttpApiIntegrationApi"
                  }
                ]
              ]
            }
          },
          "DependsOn": "HttpApiIntegrationApi"
        }
      },
      "Outputs": {
        "ServerlessDeploymentBucketName": {
          "Value": "serverless-framework-deployments-ap-south-1-742a1e34-61d6",
          "Export": {
            "Name": "sls-quiz-server-api-dev-ServerlessDeploymentBucketName"
          }
        },
        "ApiLambdaFunctionQualifiedArn": {
          "Description": "Current Lambda function version",
          "Value": {
            "Ref": "ApiLambdaVersionucJb9unkVGZN83FPovi10Pyw8aHIKK984d0FMMuw"
          },
          "Export": {
            "Name": "sls-quiz-server-api-dev-ApiLambdaFunctionQualifiedArn"
          }
        },
        "HttpApiId": {
          "Description": "Id of the HTTP API",
          "Value": {
            "Ref": "HttpApi"
          },
          "Export": {
            "Name": "sls-quiz-server-api-dev-HttpApiId"
          }
        },
        "HttpApiUrl": {
          "Description": "URL of the HTTP API",
          "Value": {
            "Fn::Join": [
              "",
              [
                "https://",
                {
                  "Ref": "HttpApi"
                },
                ".execute-api.",
                {
                  "Ref": "AWS::Region"
                },
                ".",
                {
                  "Ref": "AWS::URLSuffix"
                }
              ]
            ]
          },
          "Export": {
            "Name": "sls-quiz-server-api-dev-HttpApiUrl"
          }
        }
      }
    }
  }
}